Workbook

Sheet README
A1: UAV Harvest-Monitoring Deployment — Procurement Workbook
A2: Bill of materials for an industrial test run of the RobustIDPS.ai / M1+M4+M6+M7 network-layer robustness models on a crop harvest-readiness UAV.
A5: HOW TO USE
A6: 1 | B6: Work on the 'BOM' sheet. Each row is one line item.
A7: 2 | B7: Fill the YELLOW cells during procurement: Quoted Unit $, Vendor (confirmed), Lead time, Status.
A8: 3 | B8: Adjust BLUE cells (Qty, Unit $ Low/High estimates) to your farm size / spec.
A9: 4 | B9: BLACK cells are formulas (extended costs, totals) — do not overtype them.
A10: 5 | B10: 'Cost Summary' and 'OPEX' roll up automatically.
A12: LEGEND
A13: Blue text | B13: Editable input — quantity and cost estimates you can change.
A14: Yellow fill | B14: Fill in during procurement — quoted price, vendor, lead time, status.
A15: Black text | B15: Formula — recalculates automatically.
A17: PRIORITY
A18: Must | B18: Required for any test run.
A19: Should | B19: Strongly recommended (assurance / EW validation).
A20: Optional | B20: Add per crop / field size / budget (thermal, LiDAR, extra sensors).
A22: EXAMPLE ROW (format reference — real rows are on the BOM sheet)
A23: Item | B23: Onboard AI chip — Jetson Orin NX 16GB module
A24: Qty | B24: 1
A25: Unit $ Low / High | B25: 500 / 700
A26: Quoted Unit $ (you fill) | B26: 615
A27: Status (you fill) | B27: Ordered — PO#1042, ETA 3 wks
A29: NOTE ON PRICES | B29: All costs are indicative 2026 USD planning ranges, not quotes. Confirm with vendors for your region. Cloud + GNSS simulator can be rented (see OPEX).

Sheet BOM
A1: # | B1: Tier / Group | C1: Subsystem | D1: Function | E1: Representative part | F1: Example vendor | G1: Qty | H1: Unit $ Low | I1: Unit $ High | J1: Ext $ Low | K1: Ext $ High | L1: Quoted Unit $ | M1: Ext Quoted $ | N1: Lead (wks) | O1: Priority | P1: Status | Q1: Notes
A2: 1 | B2: UAV Platform | C2: Airframe | D2: Multirotor, >=30 min, payload >=1.5 kg | E2: DJI M350 RTK / Freefly Astro | F2: DJI / Freefly | G2: 1 | H2: 5000 | I2: 12000 | J2: =G2*H2 | K2: =G2*I2 | M2: =G2*L2 | N2: 4 | O2: Must | Q2: Fixed-wing/VTOL for >200 ha
A3: 2 | B3: UAV Platform | C3: Flight controller | D3: Open autopilot (PX4/ArduPilot) | E3: Holybro Pixhawk 6X / Cube Orange+ | F3: Holybro / CubePilot | G3: 1 | H3: 250 | I3: 450 | J3: =G3*H3 | K3: =G3*I3 | M3: =G3*L3 | N3: 3 | O3: Must | Q3: May be integrated in airframe
A4: 3 | B4: Onboard AI | C4: Embedded compute | D4: INT8 MambaShield + onboard NDVI | E4: Jetson Orin NX 16GB module | F4: NVIDIA / Seeed | G4: 1 | H4: 500 | I4: 700 | J4: =G4*H4 | K4: =G4*I4 | M4: =G4*L4 | N4: 6 | O4: Must | Q4: ~100 TOPS INT8, 10-25 W
A5: 4 | B5: Onboard AI | C5: Carrier board | D5: Jetson carrier for UAV | E5: ConnectTech Boson / Auvidea | F5: ConnectTech | G5: 1 | H5: 200 | I5: 400 | J5: =G5*H5 | K5: =G5*I5 | M5: =G5*L5 | N5: 6 | O5: Must | Q5: Pick low-SWaP carrier
A6: 5 | B6: Onboard AI | C6: Security co-accel (opt.) | D6: Dedicated INT8 detector | E6: Hailo-8 M.2 / Coral TPU | F6: Hailo / Google | G6: 1 | H6: 200 | I6: 450 | J6: =G6*H6 | K6: =G6*I6 | M6: =G6*L6 | N6: 6 | O6: Optional | Q6: 2-3 W offload of M4
A7: 6 | B7: Navigation | C7: Anti-spoof GNSS | D7: RTK + spoof/jam detection | E7: Septentrio mosaic-X5 / u-blox ZED-F9P | F7: Septentrio / u-blox | G7: 1 | H7: 300 | I7: 3000 | J7: =G7*H7 | K7: =G7*I7 | M7: =G7*L7 | N7: 6 | O7: Must | Q7: Feeds C/N0+spoof flags to M4/M6
A8: 7 | B8: Navigation | C8: GNSS antenna | D8: Multiband / anti-jam | E8: CRPA or multiband helical | F8: Tallysman / Septentrio | G8: 1 | H8: 200 | I8: 2500 | J8: =G8*H8 | K8: =G8*I8 | M8: =G8*L8 | N8: 4 | O8: Should | Q8: CRPA for serious EW
A9: 8 | B9: Datalink | C9: C2 MANET radio | D9: Encrypted mesh C2 (monitored link) | E9: Silvus StreamCaster / Doodle Labs | F9: Silvus / Doodle Labs | G9: 1 | H9: 3000 | I9: 9000 | J9: =G9*H9 | K9: =G9*I9 | M9: =G9*L9 | N9: 8 | O9: Must | Q9: The 'network layer' M1/M4 inspect
A10: 9 | B10: Datalink | C10: BVLOS backhaul | D10: 4G/5G modem + NTRIP | E10: Sierra/Quectel 5G modem | F10: Sierra Wireless | G10: 1 | H10: 150 | I10: 400 | J10: =G10*H10 | K10: =G10*I10 | M10: =G10*L10 | N10: 3 | O10: Should | Q10: Telemetry + RTK corrections
A11: 10 | B11: Datalink | C11: Backup telemetry | D11: Fail-safe C2 | E11: RFD900x | F11: RFDesign | G11: 1 | H11: 250 | I11: 500 | J11: =G11*H11 | K11: =G11*I11 | M11: =G11*L11 | N11: 3 | O11: Should | Q11: Redundant link
A12: 11 | B12: Payload | C12: Multispectral camera | D12: NDVI/NDRE harvest-due sensing | E12: MicaSense Altum-PT / RedEdge-P | F12: AgEagle/MicaSense | G12: 1 | H12: 8000 | I12: 13000 | J12: =G12*H12 | K12: =G12*I12 | M12: =G12*L12 | N12: 8 | O12: Must | Q12: Core harvest-readiness sensor
A13: 12 | B13: Payload | C13: Radiometric calibration | D13: Downwelling sensor + panel | E13: MicaSense DLS 2 + reflectance panel | F13: AgEagle/MicaSense | G13: 1 | H13: 500 | I13: 1500 | J13: =G13*H13 | K13: =G13*I13 | M13: =G13*L13 | N13: 8 | O13: Must | Q13: Essential for valid NDVI
A14: 13 | B14: Payload | C14: RGB camera (opt.) | D14: High-res scouting / ground truth | E14: Sony a7R / integrated | F14: Sony | G14: 1 | H14: 1000 | I14: 6000 | J14: =G14*H14 | K14: =G14*I14 | M14: =G14*L14 | N14: 4 | O14: Optional
A15: 14 | B15: Payload | C15: Thermal (opt.) | D15: Crop water stress | E15: FLIR Vue TZ20 | F15: Teledyne FLIR | G15: 1 | H15: 3000 | I15: 8000 | J15: =G15*H15 | K15: =G15*I15 | M15: =G15*L15 | N15: 6 | O15: Optional
A16: 15 | B16: Payload | C16: LiDAR (opt.) | D16: Biomass / canopy height | E16: DJI Zenmuse L2 / Livox | F16: DJI / Livox | G16: 1 | H16: 3000 | I16: 12000 | J16: =G16*H16 | K16: =G16*I16 | M16: =G16*L16 | N16: 6 | O16: Optional
A17: 16 | B17: Payload | C17: Gimbal | D17: Payload stabilisation | E17: Gremsy / integrated | F17: Gremsy | G17: 1 | H17: 300 | I17: 2500 | J17: =G17*H17 | K17: =G17*I17 | M17: =G17*L17 | N17: 4 | O17: Should
A18: 17 | B18: Edge Gateway | C18: Tier-2 compute | D18: Full RobustIDPS.ai + M1/M6/M7 | E18: Jetson AGX Orin 64GB (rugged) | F18: NVIDIA / ConnectTech | G18: 1 | H18: 2000 | I18: 5000 | J18: =G18*H18 | K18: =G18*I18 | M18: =G18*L18 | N18: 6 | O18: Must | Q18: ~275 TOPS; full crop-maturity model
A19: 18 | B19: Ground | C19: RTK base station | D19: cm-level corrections | E19: Emlid Reach RS3 | F19: Emlid | G19: 1 | H19: 2000 | I19: 3500 | J19: =G19*H19 | K19: =G19*I19 | M19: =G19*L19 | N19: 3 | O19: Should | Q19: Or NTRIP subscription (OPEX)
A20: 19 | B20: Ground | C20: Ground control station | D20: Mission planning + monitoring | E20: Rugged laptop/tablet + QGC | F20: Getac / Panasonic | G20: 1 | H20: 1500 | I20: 4000 | J20: =G20*H20 | K20: =G20*I20 | M20: =G20*L20 | N20: 3 | O20: Must | Q20: QGroundControl / Mission Planner
A21: 20 | B21: Ground | C21: Field networking | D21: Router + PoE switch + UPS | E21: Teltonika RUTX + PoE switch | F21: Teltonika | G21: 1 | H21: 400 | I21: 900 | J21: =G21*H21 | K21: =G21*I21 | M21: =G21*L21 | N21: 3 | O21: Should
A22: 21 | B22: Ground | C22: Field power | D22: Portable power + solar/generator | E22: 2 kWh power station + solar | F22: EcoFlow / Bluetti | G22: 1 | H22: 800 | I22: 2500 | J22: =G22*H22 | K22: =G22*I22 | M22: =G22*L22 | N22: 3 | O22: Should
A23: 22 | B23: Security | C23: Secure element | D23: Onboard key store / signed updates | E23: Microchip ATECC608 (board) | F23: Microchip | G23: 1 | H23: 20 | I23: 60 | J23: =G23*H23 | K23: =G23*I23 | M23: =G23*L23 | N23: 3 | O23: Must | Q23: Verifies PQC-signed models
A24: 23 | B24: Security | C24: HSM | D24: Sign Kyber-1024 / Dilithium updates | E24: YubiHSM 2 | F24: Yubico | G24: 1 | H24: 650 | I24: 950 | J24: =G24*H24 | K24: =G24*I24 | M24: =G24*L24 | N24: 3 | O24: Should | Q24: PQC update channel at gateway
A25: 24 | B25: Test/Validation | C25: Spectrum analyzer | D25: Measure real J/S + noise floor | E25: Signal Hound BB60 / tinySA Ultra | F25: Signal Hound | G25: 1 | H25: 500 | I25: 3500 | J25: =G25*H25 | K25: =G25*I25 | M25: =G25*L25 | N25: 3 | O25: Should | Q25: Validate field vs benchmark
A26: 25 | B26: Test/Validation | C26: GNSS sim (rent) | D26: Cabled spoof/jam replay | E26: LabSat 3 / Spirent | F26: Racelogic / Spirent | G26: 1 | H26: 1000 | I26: 20000 | J26: =G26*H26 | K26: =G26*I26 | M26: =G26*L26 | N26: 4 | O26: Should | Q26: Rental OK; range/Faraday only
A27: 26 | B27: Test/Validation | C27: SDR | D27: RF characterisation | E27: USRP B210 / HackRF | F27: Ettus / Great Scott | G27: 1 | H27: 300 | I27: 3000 | J27: =G27*H27 | K27: =G27*I27 | M27: =G27*L27 | N27: 3 | O27: Optional
A28: 27 | B28: Consumables | C28: Flight batteries | D28: Smart LiPo/Li-ion packs | E28: OEM smart batteries | F28: OEM | G28: 8 | H28: 200 | I28: 600 | J28: =G28*H28 | K28: =G28*I28 | M28: =G28*L28 | N28: 3 | O28: Must | Q28: Rotate 6-10 packs
A29: 28 | B29: Consumables | C29: Charging | D29: Multi-charger + LiPo bags | E29: Fast multi-charger | F29: OEM | G29: 1 | H29: 300 | I29: 1200 | J29: =G29*H29 | K29: =G29*I29 | M29: =G29*L29 | N29: 3 | O29: Must
A30: 29 | B30: Tools | C30: Assembly toolkit | D30: Drivers, solder, multimeter, crimpers | E30: Precision toolkit | F30: iFixit / Weller | G30: 1 | H30: 300 | I30: 1500 | J30: =G30*H30 | K30: =G30*I30 | M30: =G30*L30 | N30: 2 | O30: Must
A31: 30 | B31: Logistics | C31: Transit cases | D31: Rugged transport | E31: Pelican / SKB | F31: Pelican | G31: 3 | H31: 150 | I31: 400 | J31: =G31*H31 | K31: =G31*I31 | M31: =G31*L31 | N31: 3 | O31: Should
A32: 31 | B32: Logistics | C32: Field accessories | D32: Landing pad, GCP targets, ND filters | E32: Assorted | F32: Assorted | G32: 1 | H32: 200 | I32: 800 | J32: =G32*H32 | K32: =G32*I32 | M32: =G32*L32 | N32: 2 | O32: Should
A33: 32 | B33: Safety | C33: Safety kit | D33: Li-ion extinguisher, first aid, hi-vis | E33: Safety kit | F33: Assorted | G33: 1 | H33: 200 | I33: 600 | J33: =G33*H33 | K33: =G33*I33 | M33: =G33*L33 | N33: 2 | O33: Must
A34: TOTAL (est. range) | J34: =SUM(J2:J33) | K34: =SUM(K2:K33) | M34: =SUM(M2:M33)

Sheet Cost Summary
A1: Cost Summary
A2: Rolls up from the BOM sheet. Estimated ranges; Quoted column fills as you procure.
A4: Tier / Group | B4: Est $ Low | C4: Est $ High | D4: Quoted $
A5: UAV Platform | B5: =SUMIFS(BOM!$J$2:$J$33,BOM!$B$2:$B$33,$A5) | C5: =SUMIFS(BOM!$K$2:$K$33,BOM!$B$2:$B$33,$A5) | D5: =SUMIFS(BOM!$M$2:$M$33,BOM!$B$2:$B$33,$A5)
A6: Onboard AI | B6: =SUMIFS(BOM!$J$2:$J$33,BOM!$B$2:$B$33,$A6) | C6: =SUMIFS(BOM!$K$2:$K$33,BOM!$B$2:$B$33,$A6) | D6: =SUMIFS(BOM!$M$2:$M$33,BOM!$B$2:$B$33,$A6)
A7: Navigation | B7: =SUMIFS(BOM!$J$2:$J$33,BOM!$B$2:$B$33,$A7) | C7: =SUMIFS(BOM!$K$2:$K$33,BOM!$B$2:$B$33,$A7) | D7: =SUMIFS(BOM!$M$2:$M$33,BOM!$B$2:$B$33,$A7)
A8: Datalink | B8: =SUMIFS(BOM!$J$2:$J$33,BOM!$B$2:$B$33,$A8) | C8: =SUMIFS(BOM!$K$2:$K$33,BOM!$B$2:$B$33,$A8) | D8: =SUMIFS(BOM!$M$2:$M$33,BOM!$B$2:$B$33,$A8)
A9: Payload | B9: =SUMIFS(BOM!$J$2:$J$33,BOM!$B$2:$B$33,$A9) | C9: =SUMIFS(BOM!$K$2:$K$33,BOM!$B$2:$B$33,$A9) | D9: =SUMIFS(BOM!$M$2:$M$33,BOM!$B$2:$B$33,$A9)
A10: Edge Gateway | B10: =SUMIFS(BOM!$J$2:$J$33,BOM!$B$2:$B$33,$A10) | C10: =SUMIFS(BOM!$K$2:$K$33,BOM!$B$2:$B$33,$A10) | D10: =SUMIFS(BOM!$M$2:$M$33,BOM!$B$2:$B$33,$A10)
A11: Ground | B11: =SUMIFS(BOM!$J$2:$J$33,BOM!$B$2:$B$33,$A11) | C11: =SUMIFS(BOM!$K$2:$K$33,BOM!$B$2:$B$33,$A11) | D11: =SUMIFS(BOM!$M$2:$M$33,BOM!$B$2:$B$33,$A11)
A12: Security | B12: =SUMIFS(BOM!$J$2:$J$33,BOM!$B$2:$B$33,$A12) | C12: =SUMIFS(BOM!$K$2:$K$33,BOM!$B$2:$B$33,$A12) | D12: =SUMIFS(BOM!$M$2:$M$33,BOM!$B$2:$B$33,$A12)
A13: Test/Validation | B13: =SUMIFS(BOM!$J$2:$J$33,BOM!$B$2:$B$33,$A13) | C13: =SUMIFS(BOM!$K$2:$K$33,BOM!$B$2:$B$33,$A13) | D13: =SUMIFS(BOM!$M$2:$M$33,BOM!$B$2:$B$33,$A13)
A14: Consumables | B14: =SUMIFS(BOM!$J$2:$J$33,BOM!$B$2:$B$33,$A14) | C14: =SUMIFS(BOM!$K$2:$K$33,BOM!$B$2:$B$33,$A14) | D14: =SUMIFS(BOM!$M$2:$M$33,BOM!$B$2:$B$33,$A14)
A15: Tools | B15: =SUMIFS(BOM!$J$2:$J$33,BOM!$B$2:$B$33,$A15) | C15: =SUMIFS(BOM!$K$2:$K$33,BOM!$B$2:$B$33,$A15) | D15: =SUMIFS(BOM!$M$2:$M$33,BOM!$B$2:$B$33,$A15)
A16: Logistics | B16: =SUMIFS(BOM!$J$2:$J$33,BOM!$B$2:$B$33,$A16) | C16: =SUMIFS(BOM!$K$2:$K$33,BOM!$B$2:$B$33,$A16) | D16: =SUMIFS(BOM!$M$2:$M$33,BOM!$B$2:$B$33,$A16)
A17: Safety | B17: =SUMIFS(BOM!$J$2:$J$33,BOM!$B$2:$B$33,$A17) | C17: =SUMIFS(BOM!$K$2:$K$33,BOM!$B$2:$B$33,$A17) | D17: =SUMIFS(BOM!$M$2:$M$33,BOM!$B$2:$B$33,$A17)
A18: CAPEX TOTAL | B18: =SUM(B5:B17) | C18: =SUM(C5:C17) | D18: =SUM(D5:D17)
A21: By priority
A22: Priority | B22: Est $ Low | C22: Est $ High | D22: Quoted $
A23: Must | B23: =SUMIFS(BOM!$J$2:$J$33,BOM!$O$2:$O$33,$A23) | C23: =SUMIFS(BOM!$K$2:$K$33,BOM!$O$2:$O$33,$A23) | D23: =SUMIFS(BOM!$M$2:$M$33,BOM!$O$2:$O$33,$A23)
A24: Should | B24: =SUMIFS(BOM!$J$2:$J$33,BOM!$O$2:$O$33,$A24) | C24: =SUMIFS(BOM!$K$2:$K$33,BOM!$O$2:$O$33,$A24) | D24: =SUMIFS(BOM!$M$2:$M$33,BOM!$O$2:$O$33,$A24)
A25: Optional | B25: =SUMIFS(BOM!$J$2:$J$33,BOM!$O$2:$O$33,$A25) | C25: =SUMIFS(BOM!$K$2:$K$33,BOM!$O$2:$O$33,$A25) | D25: =SUMIFS(BOM!$M$2:$M$33,BOM!$O$2:$O$33,$A25)
A27: Lean first run = "Must" only. Full assurance = Must + Should. Optional = crop/field-specific add-ons.

Sheet OPEX
A1: Recurring Costs (OPEX)
A2: Monthly services and consumable-rate items. Fill blue estimates for your setup.
A4: Item | B4: Purpose | C4: $ / month (Low) | D4: $ / month (High) | E4: $ / year (Low) | F4: $ / year (High)
A5: Cloud GPU (FedGTD + PQC signing) | B5: Tier-3 aggregation & model signing | C5: 300 | D5: 1500 | E5: =C5*12 | F5: =D5*12
A6: NTRIP correction subscription | B6: RTK corrections (if no own base) | C6: 20 | D6: 100 | E6: =C6*12 | F6: =D6*12
A7: Connectivity SIM / data plan | B7: BVLOS 4G/5G backhaul | C7: 30 | D7: 150 | E7: =C7*12 | F7: =D7*12
A8: Liability / hull insurance | B8: Ops insurance | C8: 100 | D8: 400 | E8: =C8*12 | F8: =D8*12
A9: Software maintenance / updates | B9: Model retraining, container upkeep | C9: 100 | D9: 500 | E9: =C9*12 | F9: =D9*12
A10: GNSS simulator rental (test window) | B10: EW validation, per month when testing | C10: 0 | D10: 3000 | E10: =C10*12 | F10: =D10*12
A11: TOTAL OPEX | C11: =SUM(C5:C10) | D11: =SUM(D5:D10) | E11: =SUM(E5:E10) | F11: =SUM(F5:F10)
